packageankit1/AnovaTest.py
packageankit1/__init__.py
packageankit1-0.0.1.dist-info/License.txt
packageankit1-0.0.1.dist-info/METADATA
packageankit1-0.0.1.dist-info/WHEEL
packageankit1-0.0.1.dist-info/top_level.txt
packageankit1-0.0.1.dist-info/RECORD
