Metadata-Version: 2.1
Name: packageankit1
Version: 0.0.1
Summary: ANOVA Python
Home-page: UNKNOWN
Author: Ankit Tiwari
Author-email: ankittiwari123321@gmail.com
License: UNKNOWN
Keywords: python,ANOVA,SSB,SSW,Ankit Tiwari
Platform: UNKNOWN
Classifier: Development Status :: 1 - Planning
Classifier: Intended Audience :: Developers
Classifier: Programming Language :: Python :: 3
Classifier: Operating System :: Unix
Classifier: Operating System :: MacOS :: MacOS X
Classifier: Operating System :: Microsoft :: Windows
License-File: License.txt
Requires-Dist: pandas
Requires-Dist: numpy
